pyuntappd/__init__.py
pyuntappd-0.0.5.dist-info/METADATA
pyuntappd-0.0.5.dist-info/RECORD
pyuntappd-0.0.5.dist-info/WHEEL
pyuntappd-0.0.5.dist-info/top_level.txt
