Metadata-Version: 2.1
Name: pyuntappd
Version: 0.0.5
Summary: UNKNOWN
Home-page: https://gitlab.com/ludeeus/pyuntappd
Author: Joakim Sorensen
Author-email: joasoe@gmail.com
License: UNKNOWN
Platform: UNKNOWN
Classifier: Programming Language :: Python :: 3
Classifier: License :: OSI Approved :: MIT License
Classifier: Operating System :: OS Independent
